{
  "name": "Forte Dev Environment",
  "dockerComposeFile": "docker-compose.yml",
  "service": "app",
  "workspaceFolder": "/workspace",
  "features": {
    "ghcr.io/devcontainers/features/node:1": {
      "version": "lts"
    },
    "ghcr.io/devcontainers/features/common-utils:2": {}
  },
  "customizations": {
    "vscode": {
      "extensions": [
        "tamasfe.even-better-toml",
        "dbaeumer.vscode-eslint",
        "esbenp.prettier-vscode",
        "rust-lang.rust-analyzer"
      ]
    }
  },
  "forwardPorts": [3000],
  "remoteUser": "vscode"
}
